betanin/__init__.py
betanin/application.py
betanin/beets.py
betanin/blueprints.py
betanin/events.py
betanin/extensions.py
betanin/models.py
betanin/notifications.py
betanin/paths.py
betanin/status.py
betanin/system_info.py
betanin/version.txt
betanin/config/__init__.py
betanin/config/betanin.py
betanin/config/flask.py
betanin/config/secret_key.py
betanin/entry/__init__.py
betanin/entry/betanin.py
betanin/entry/shell.py
betanin/jobs/__init__.py
betanin/jobs/import_torrents.py
betanin/jobs/serve_web.py
betanin/rest/__init__.py
betanin/rest/base.py
betanin/rest/namespaces.py
betanin/rest_models/__init__.py
betanin/rest_models/request.py
betanin/rest_models/response.py
betanin/rest_resources/__init__.py
betanin/rest_resources/authentication.py
betanin/rest_resources/beets.py
betanin/rest_resources/meta.py
betanin/rest_resources/notifications.py
betanin/rest_resources/torrent_clients.py
betanin/rest_resources/torrents.py
betanin_client/__init__.py
betanin_client/dist/index.html
betanin_client/dist/manifest.json
betanin_client/dist/css/app.703a353b.css
betanin_client/dist/css/chunk-vendors.ee068850.css
betanin_client/dist/fonts/materialdesignicons-webfont.147e3378.woff
betanin_client/dist/fonts/materialdesignicons-webfont.174c02fc.ttf
betanin_client/dist/fonts/materialdesignicons-webfont.64d4cf64.eot
betanin_client/dist/fonts/materialdesignicons-webfont.7a44ea19.woff2
betanin_client/dist/icons/android-icon-144x144.png
betanin_client/dist/icons/android-icon-192x192.png
betanin_client/dist/icons/android-icon-36x36.png
betanin_client/dist/icons/android-icon-48x48.png
betanin_client/dist/icons/android-icon-72x72.png
betanin_client/dist/icons/android-icon-96x96.png
betanin_client/dist/icons/apple-icon-114x114.png
betanin_client/dist/icons/apple-icon-120x120.png
betanin_client/dist/icons/apple-icon-144x144.png
betanin_client/dist/icons/apple-icon-152x152.png
betanin_client/dist/icons/apple-icon-180x180.png
betanin_client/dist/icons/apple-icon-57x57.png
betanin-0.5.6.dist-info/LICENSE
betanin-0.5.6.dist-info/METADATA
betanin-0.5.6.dist-info/WHEEL
betanin-0.5.6.dist-info/entry_points.txt
betanin-0.5.6.dist-info/top_level.txt
betanin-0.5.6.dist-info/RECORD
