Metadata-Version: 2.1
Name: betanin
Version: 0.5.6
Summary: beets based mitm of your torrent client and music player
Author-email: Senan Kelly <senan@senan.xyz>
Project-URL: Homepage, https://github.com/sentriz/betanin
Project-URL: Bug Tracker, https://github.com/sentriz/betanin/issues
Classifier: Programming Language :: Python :: 3
Classifier: License :: OSI Approved :: MIT License
Classifier: Operating System :: OS Independent
Requires-Python: >=3.8
License-File: LICENSE
Requires-Dist: beets
Requires-Dist: apprise
Requires-Dist: alembic
Requires-Dist: click
Requires-Dist: Flask <3.0.0
Requires-Dist: Flask-Cors
Requires-Dist: Flask-JWT-Extended
Requires-Dist: Flask-Migrate
Requires-Dist: flask-restx
Requires-Dist: Flask-SocketIO
Requires-Dist: Flask-SQLAlchemy
Requires-Dist: gevent
Requires-Dist: pyxdg
Requires-Dist: loguru
Requires-Dist: ptyprocess
Requires-Dist: python-engineio
Requires-Dist: python-socketio
Requires-Dist: SQLAlchemy
Requires-Dist: SQLAlchemy-Utils
Requires-Dist: toml
Provides-Extra: dev
Requires-Dist: isort >=4.3.1 ; extra == 'dev'
Requires-Dist: toml ; extra == 'dev'
Requires-Dist: pyproject ; extra == 'dev'
Requires-Dist: black ; extra == 'dev'
Requires-Dist: autoflake ; extra == 'dev'
Requires-Dist: pyright ; extra == 'dev'
Requires-Dist: pylint ; extra == 'dev'
